tests/__init__.py
zeebe_grpc/__init__.py
zeebe_grpc/gateway_pb2.py
zeebe_grpc/gateway_pb2_grpc.py
zeebe_grpc-8.4.13.dist-info/LICENSE
zeebe_grpc-8.4.13.dist-info/METADATA
zeebe_grpc-8.4.13.dist-info/WHEEL
zeebe_grpc-8.4.13.dist-info/top_level.txt
zeebe_grpc-8.4.13.dist-info/RECORD
