Metadata-Version: 2.1
Name: zeebe-grpc
Version: 8.4.13
Summary: zeebe Python gRPC Gateway
Home-page: https://gitlab.com/stephane.ludwig/zeebe_python_grpc
Author: Stéphane Ludwig
Author-email: gitlab@stephane-ludwig.net
Classifier: Programming Language :: Python :: 3
Classifier: License :: OSI Approved :: MIT License
Classifier: Operating System :: OS Independent
License-File: LICENSE
